openfermionpyscf/__init__.py
openfermionpyscf/_pyscf_molecular_data.py
openfermionpyscf/_run_pyscf.py
openfermionpyscf/_run_pyscf_test.py
openfermionpyscf/_version.py
openfermionpyscf-0.5.dist-info/LICENSE
openfermionpyscf-0.5.dist-info/METADATA
openfermionpyscf-0.5.dist-info/NOTICE
openfermionpyscf-0.5.dist-info/WHEEL
openfermionpyscf-0.5.dist-info/top_level.txt
openfermionpyscf-0.5.dist-info/RECORD
