Metadata-Version: 1.0
Name: openfermionpyscf
Version: 0.5
Summary: A plugin allowing OpenFermion to interface with PySCF.
Home-page: http://www.openfermion.org
Author: The OpenFermion Developers
Author-email: help@openfermion.org
License: Apache 2
Platform: UNKNOWN
